MANIFEST.in
README
setup.cfg
setup.py
BuzzAlgoTrade.egg-info/PKG-INFO
BuzzAlgoTrade.egg-info/SOURCES.txt
BuzzAlgoTrade.egg-info/dependency_links.txt
BuzzAlgoTrade.egg-info/requires.txt
BuzzAlgoTrade.egg-info/top_level.txt
pyalgotrade/__init__.py
pyalgotrade/bar.py
pyalgotrade/dispatcher.py
pyalgotrade/dispatchprio.py
pyalgotrade/eventprofiler.py
pyalgotrade/logger.py
pyalgotrade/marketsession.py
pyalgotrade/observer.py
pyalgotrade/plotter.py
pyalgotrade/resamplebase.py
pyalgotrade/warninghelpers.py
pyalgotrade/barfeed/__init__.py
pyalgotrade/barfeed/common.py
pyalgotrade/barfeed/csvfeed.py
pyalgotrade/barfeed/dbfeed.py
pyalgotrade/barfeed/googlefeed.py
pyalgotrade/barfeed/membf.py
pyalgotrade/barfeed/ninjatraderfeed.py
pyalgotrade/barfeed/quandlfeed.py
pyalgotrade/barfeed/resampled.py
pyalgotrade/barfeed/sqlitefeed.py
pyalgotrade/barfeed/yahoofeed.py
pyalgotrade/bitcoincharts/__init__.py
pyalgotrade/bitcoincharts/barfeed.py
pyalgotrade/bitstamp/__init__.py
pyalgotrade/bitstamp/barfeed.py
pyalgotrade/bitstamp/broker.py
pyalgotrade/bitstamp/common.py
pyalgotrade/bitstamp/httpclient.py
pyalgotrade/bitstamp/livebroker.py
pyalgotrade/bitstamp/livefeed.py
pyalgotrade/bitstamp/wsclient.py
pyalgotrade/broker/__init__.py
pyalgotrade/broker/backtesting.py
pyalgotrade/broker/fillstrategy.py
pyalgotrade/broker/slippage.py
pyalgotrade/dataseries/__init__.py
pyalgotrade/dataseries/aligned.py
pyalgotrade/dataseries/bards.py
pyalgotrade/dataseries/resampled.py
pyalgotrade/feed/__init__.py
pyalgotrade/feed/csvfeed.py
pyalgotrade/feed/memfeed.py
pyalgotrade/optimizer/__init__.py
pyalgotrade/optimizer/base.py
pyalgotrade/optimizer/local.py
pyalgotrade/optimizer/server.py
pyalgotrade/optimizer/worker.py
pyalgotrade/optimizer/xmlrpcserver.py
pyalgotrade/stratanalyzer/__init__.py
pyalgotrade/stratanalyzer/drawdown.py
pyalgotrade/stratanalyzer/returns.py
pyalgotrade/stratanalyzer/sharpe.py
pyalgotrade/stratanalyzer/trades.py
pyalgotrade/strategy/__init__.py
pyalgotrade/strategy/position.py
pyalgotrade/talibext/__init__.py
pyalgotrade/talibext/indicator.py
pyalgotrade/technical/__init__.py
pyalgotrade/technical/atr.py
pyalgotrade/technical/bollinger.py
