Metadata-Version: 1.0
Name: BuzzAlgoTrade
Version: 0.0.2
Summary: Python Algorithmic Trading
Home-page: UNKNOWN
Author: BuzzPoem
Author-email: leotam@buzzpoem.com
License: UNKNOWN
Platform: UNKNOWN
